flake8_one_letter_variables_check/__init__.py
flake8_one_letter_variables_check/flake8_one_letter_variables.py
flake8_one_letter_variables_check-0.1.0.dist-info/LICENSE
flake8_one_letter_variables_check-0.1.0.dist-info/METADATA
flake8_one_letter_variables_check-0.1.0.dist-info/WHEEL
flake8_one_letter_variables_check-0.1.0.dist-info/RECORD
