Metadata-Version: 2.1
Name: flake8_one_letter_variables_check
Version: 0.1.0
Summary: flake8 plugin for checking out one-letter variables
Home-page: https://github.com/Daku-on/flake8-one-variable-check/
License: MIT
Author: Dakuon
Author-email: 113434878+Daku-on@users.noreply.github.com
Requires-Python: >=3.10,<4.0
Classifier: License :: OSI Approved :: MIT License
Classifier: Programming Language :: Python :: 3
Classifier: Programming Language :: Python :: 3.10
Classifier: Programming Language :: Python :: 3.11
Classifier: Programming Language :: Python :: 3.12
Requires-Dist: flake8 (>=7.0.0,<8.0.0)
Project-URL: Repository, https://github.com/Daku-on/flake8-one-variable-check/
